pytest_simbind/DataSink.py
pytest_simbind/SimbindCollector.py
pytest_simbind/SimbindCorePlugin.py
pytest_simbind/TestLogHandler.py
pytest_simbind/__init__.py
pytest_simbind/fixture.py
pytest_simbind/plugin.py
pytest_simbind/dto/FailDetailsDto.py
pytest_simbind/dto/LogMessageDto.py
pytest_simbind/dto/TestCaseInfoDto.py
pytest_simbind/dto/TestDataRecordDto.py
pytest_simbind/dto/TestStatusDto.py
pytest_simbind/dto/TestUpdateDto.py
pytest_simbind/dto/__init__.py
pytest_simbind-0.1.2.dist-info/LICENSE
pytest_simbind-0.1.2.dist-info/METADATA
pytest_simbind-0.1.2.dist-info/WHEEL
pytest_simbind-0.1.2.dist-info/entry_points.txt
pytest_simbind-0.1.2.dist-info/top_level.txt
pytest_simbind-0.1.2.dist-info/RECORD
