Metadata-Version: 2.1
Name: pytest-simbind
Version: 0.1.2
Summary: Pytest plugin to operate with objects generated by Simbind tool.
Author-email: SWAG Engineering UG <contact@swag-engineering.io>
License: GNU AFFERO GENERAL PUBLIC LICENSE
Project-URL: Documentation, https://github.com/swag-engineering/pytest-simbind/wiki
Project-URL: Repository, https://github.com/swag-engineering/pytest-simbind
Classifier: Framework :: Pytest
Classifier: Intended Audience :: Developers
Classifier: License :: OSI Approved :: GNU Affero General Public License v3
Classifier: Topic :: Software Development :: Testing
Classifier: Topic :: Software Development :: Quality Assurance
Classifier: Topic :: Utilities
Classifier: Environment :: Console
Classifier: Programming Language :: Python
Classifier: Programming Language :: Python :: 3
Classifier: Programming Language :: Python :: 3 :: Only
Classifier: Programming Language :: Python :: 3.10
Classifier: Programming Language :: Python :: 3.11
Classifier: Programming Language :: Python :: 3.12
Requires-Python: >=3.10
License-File: LICENSE
Requires-Dist: pytest >=7.0.0
